secdaily/SecDaily.py
secdaily/_00_common/BaseDefinitions.py
secdaily/_00_common/DBBase.py
secdaily/_00_common/DBDebugUtils.py
secdaily/_00_common/DebugUtils.py
secdaily/_00_common/DownloadUtils.py
secdaily/_00_common/MigrationProcessing.py
secdaily/_00_common/ParallelExecution.py
secdaily/_00_common/ProcessBase.py
secdaily/_00_common/SecFileUtils.py
secdaily/_00_common/Sponsoring.py
secdaily/_00_common/Version.py
secdaily/_00_common/__init__.py
secdaily/_00_common/db/StateAccess.py
secdaily/_00_common/db/__init__.py
secdaily/_00_common/sql/V1__Create_SecReports_table.sql
secdaily/_00_common/sql/V2__Create_SecFullIndex_table.sql
secdaily/_00_common/sql/V3__Create_SecReportProcessing_table.sql
secdaily/_00_common/sql/V4__Create_MassTesting_tables.sql
secdaily/_00_common/sql/V5__Create_State_table.sql
secdaily/_00_common/testdata/cday-10k_20201231_htm.xml
secdaily/_00_common/testdata/cday-20201231_pre.xml
secdaily/_00_common/testdata/cohu-20201226_pre.xml
secdaily/_00_common/testdata/cohu20201226_10k_htm.xml
secdaily/_00_common/testdata/grsv-10k_20201231_htm.xml
secdaily/_00_common/testdata/grsv-20201231_pre.xml
secdaily/_00_common/testdata/nymt-20201231_htm.xml
secdaily/_00_common/testdata/nymt-20201231_pre.xml
secdaily/_00_common/testdata/oii-20201231_htm.xml
secdaily/_00_common/testdata/oii-20201231_pre.xml
secdaily/_00_common/testdata/urg-20201231_pre.xml
secdaily/_00_common/testdata/urg_10k_htm.xml
secdaily/_00_common/testdata/wtfc-20201231_htm.xml
secdaily/_00_common/testdata/wtfc-20201231_pre.xml
secdaily/_01_index/SecFullIndexFilePostProcessing.py
secdaily/_01_index/SecFullIndexFileProcessing.py
secdaily/_01_index/__init__.py
secdaily/_01_index/db/IndexPostProcessingDataAccess.py
secdaily/_01_index/db/IndexProcessingDataAccess.py
secdaily/_01_index/db/__init__.py
secdaily/_02_xml/SecXmlFileDownloading.py
secdaily/_02_xml/SecXmlFileParsing.py
secdaily/_02_xml/SecXmlFilePreProcessing.py
secdaily/_02_xml/__init__.py
secdaily-0.2.2.dist-info/METADATA
secdaily-0.2.2.dist-info/WHEEL
secdaily-0.2.2.dist-info/RECORD
