Metadata-Version: 2.3
Name: secdaily
Version: 0.2.2
Summary: A tool that replicates the quarterly Financial Statement Datasets from the SEC (https://www.sec.gov/dera/data/financial-statement-data-sets), but on a daily basis.
License: Apache-2.0
Keywords: SEC.GOV,SEC EDGAR,SEC Filing,EDGAR,Finance,CIK,10-Q,10-K,Financial Statements,Financial Statements Dataset,Financial Analysis,Data Processing,Financial Data,SEC API,XBRL
Author: Hansjoerg
Author-email: hansjoeg.wingeier@gmail.com
Maintainer: Hansjoerg Wingeier
Maintainer-email: hansjoeg.wingeier@gmail.com
Requires-Python: >=3.10
Classifier: Development Status :: 5 - Production/Stable
Classifier: Programming Language :: Python :: 3
Classifier: Programming Language :: Python :: 3.10
Classifier: Programming Language :: Python :: 3.11
Classifier: Programming Language :: Python :: 3.12
Classifier: License :: OSI Approved :: Apache Software License
Classifier: Operating System :: OS Independent
Classifier: Topic :: Office/Business :: Financial
Classifier: Topic :: Office/Business :: Financial :: Investment
Classifier: Intended Audience :: Developers
Classifier: Intended Audience :: Financial and Insurance Industry
Classifier: Topic :: Software Development :: Libraries :: Python Modules
Classifier: Topic :: Utilities
Classifier: Natural Language :: English
Provides-Extra: dev
Requires-Dist: black ; extra == "dev"
Requires-Dist: lxml (>=4.8.0)
Requires-Dist: pandas (>=2.2.0)
Requires-Dist: pathos (>=0.3.0)
Requires-Dist: pyarrow (>=19.0.0)
Requires-Dist: pylint ; extra == "dev"
Requires-Dist: pytest ; extra == "dev"
Requires-Dist: requests (>=2.32.0)
Requires-Dist: ruff ; extra == "dev"
Project-URL: Bug Tracker, https://github.com/HansjoergW/sec-financial-statement-data-set-daily-processing/issues
Project-URL: Change Log, https://github.com/HansjoergW/sec-financial-statement-data-set-daily-processing/blob/main/CHANGELOG.md
Project-URL: Funding, https://github.com/sponsors/HansjoergW
Project-URL: Forum, https://github.com/HansjoergW/sec-financial-statement-data-set-daily-processing/discussions
Project-URL: Github, https://github.com/HansjoergW/sec-financial-statement-data-set-daily-processing
Project-URL: Homepage, https://hansjoergw.github.io/sec-financial-statement-data-set-daily-processing/
